huaweicloudsdkbcs/__init__.py
huaweicloudsdkbcs/v2/__init__.py
huaweicloudsdkbcs/v2/bcs_async_client.py
huaweicloudsdkbcs/v2/bcs_client.py
huaweicloudsdkbcs/v2/model/__init__.py
huaweicloudsdkbcs/v2/model/basic_info.py
huaweicloudsdkbcs/v2/model/batch_add_peers_to_channel_request.py
huaweicloudsdkbcs/v2/model/batch_add_peers_to_channel_request_body.py
huaweicloudsdkbcs/v2/model/batch_add_peers_to_channel_response.py
huaweicloudsdkbcs/v2/model/batch_create_channels_request.py
huaweicloudsdkbcs/v2/model/batch_create_channels_request_body.py
huaweicloudsdkbcs/v2/model/batch_create_channels_response.py
huaweicloudsdkbcs/v2/model/batch_invite_members_to_channel_request.py
huaweicloudsdkbcs/v2/model/batch_invite_members_to_channel_request_body.py
huaweicloudsdkbcs/v2/model/batch_invite_members_to_channel_response.py
huaweicloudsdkbcs/v2/model/batch_remove_orgs_from_channel_request.py
huaweicloudsdkbcs/v2/model/batch_remove_orgs_from_channel_request_body.py
huaweicloudsdkbcs/v2/model/batch_remove_orgs_from_channel_response.py
huaweicloudsdkbcs/v2/model/batch_remove_peers_from_channel_request.py
huaweicloudsdkbcs/v2/model/batch_remove_peers_from_channel_request_body.py
huaweicloudsdkbcs/v2/model/batch_remove_peers_from_channel_response.py
huaweicloudsdkbcs/v2/model/blockchain_info.py
huaweicloudsdkbcs/v2/model/cce_cluster_info.py
huaweicloudsdkbcs/v2/model/cce_create_info.py
huaweicloudsdkbcs/v2/model/cfg_request_body.py
huaweicloudsdkbcs/v2/model/channel.py
huaweicloudsdkbcs/v2/model/channel_create_info.py
huaweicloudsdkbcs/v2/model/channel_info.py
huaweicloudsdkbcs/v2/model/channel_info_v2.py
huaweicloudsdkbcs/v2/model/com_cce.py
huaweicloudsdkbcs/v2/model/couch_db.py
huaweicloudsdkbcs/v2/model/couch_db_info.py
huaweicloudsdkbcs/v2/model/create_blockchain_cert_by_user_name_request.py
huaweicloudsdkbcs/v2/model/create_blockchain_cert_by_user_name_request_body.py
huaweicloudsdkbcs/v2/model/create_blockchain_cert_by_user_name_response.py
huaweicloudsdkbcs-3.1.184.dist-info/METADATA
huaweicloudsdkbcs-3.1.184.dist-info/WHEEL
huaweicloudsdkbcs-3.1.184.dist-info/licenses/LICENSE
huaweicloudsdkbcs-3.1.184.dist-info/RECORD
